imppkg/__init__.py
imppkg/data.json
imppkg/harmonic_mean.c
imppkg/harmonic_mean.cp310-win_amd64.pyd
imppkg/harmonic_mean.pyx
imppkg/harmony.py
imppkg/py.typed
pubpypack_harmony_david_tozer-0.0.3.dist-info/LICENSE
pubpypack_harmony_david_tozer-0.0.3.dist-info/METADATA
pubpypack_harmony_david_tozer-0.0.3.dist-info/WHEEL
pubpypack_harmony_david_tozer-0.0.3.dist-info/entry_points.txt
pubpypack_harmony_david_tozer-0.0.3.dist-info/top_level.txt
pubpypack_harmony_david_tozer-0.0.3.dist-info/RECORD
