Metadata-Version: 2.1
Name: pubpypack-harmony-david-tozer
Version: 0.0.3
Summary: This package does amazing things.
Home-page: https://github.com/freelance-dave/publishing-python-packages.git
Author: David Tozer
Author-email: "David Tozer" <cpp.sage@gmail.com>
License: MIT
Classifier: License :: OSI Approved :: MIT License
Requires-Python: >=3.9
License-File: LICENSE
Requires-Dist: termcolor (<2,>=1.1.0)
